napbots/__init__.py
napbots/example.py
napbots/api/__init__.py
napbots/api/authentication/__init__.py
napbots/api/authentication/auth.py
napbots/api/base/__init__.py
napbots/api/base/base.py
napbots/api/client/__init__.py
napbots/api/client/client.py
napbots/api/data/__init__.py
napbots/api/data/model.py
napbots/api/data/serializable.py
napbots-0.1.1.dist-info/LICENSE
napbots-0.1.1.dist-info/METADATA
napbots-0.1.1.dist-info/WHEEL
napbots-0.1.1.dist-info/top_level.txt
napbots-0.1.1.dist-info/RECORD
